django_commons_best_practices/__init__.py
django_commons_best_practices/playground.py
django_commons_best_practices-1.2.0.dist-info/LICENSE
django_commons_best_practices-1.2.0.dist-info/METADATA
django_commons_best_practices-1.2.0.dist-info/WHEEL
django_commons_best_practices-1.2.0.dist-info/top_level.txt
django_commons_best_practices-1.2.0.dist-info/RECORD
